nekoconf/__init__.py
nekoconf/_version.py
nekoconf/cli/__init__.py
nekoconf/cli/main.py
nekoconf/core/__init__.py
nekoconf/core/config.py
nekoconf/event/__init__.py
nekoconf/event/changes.py
nekoconf/event/handler.py
nekoconf/event/match.py
nekoconf/event/pipeline.py
nekoconf/event/transaction.py
nekoconf/event/type.py
nekoconf/schema/__init__.py
nekoconf/schema/validator.py
nekoconf/server/__init__.py
nekoconf/server/app.py
nekoconf/server/auth.py
nekoconf/server/html/config.html
nekoconf/server/html/favicon.ico
nekoconf/server/html/index.html
nekoconf/server/html/login.html
nekoconf/server/html/static/logo.svg
nekoconf/server/html/static/css/nekoconf.css
nekoconf/server/html/static/js/config.js
nekoconf/server/html/static/js/dashboard.js
nekoconf/storage/__init__.py
nekoconf/storage/base.py
nekoconf/storage/file.py
nekoconf/storage/remote.py
nekoconf/utils/__init__.py
nekoconf/utils/env.py
nekoconf/utils/helper.py
nekoconf-1.2.1.dist-info/licenses/LICENSE
nekoconf-1.2.1.dist-info/METADATA
nekoconf-1.2.1.dist-info/WHEEL
nekoconf-1.2.1.dist-info/entry_points.txt
nekoconf-1.2.1.dist-info/top_level.txt
nekoconf-1.2.1.dist-info/RECORD
