Metadata-Version: 2.4
Name: nekoconf
Version: 1.2.1
Summary: NekoConf - A cute configuration manager for your JSON and YAML configuration files
Author-email: "Nya Foundation Team (k3scat)" <k3scat@github.com>
License-Expression: MIT
Project-URL: Homepage, https://github.com/nya-foundation/nekoconf
Project-URL: Bug Tracker, https://github.com/nya-foundation/nekoconf/issues
Classifier: Development Status :: 4 - Beta
Classifier: Intended Audience :: Developers
Classifier: Programming Language :: Python :: 3.10
Classifier: Programming Language :: Python :: 3.11
Classifier: Programming Language :: Python :: 3.12
Classifier: Programming Language :: Python :: 3.13
Requires-Python: >=3.10
License-File: LICENSE
Requires-Dist: pyyaml>=6.0
Requires-Dist: colorlog>=6.0.0
Requires-Dist: tomli>=2.0.0
Requires-Dist: tomli-w>=1.0.0
Provides-Extra: server
Requires-Dist: fastapi>=0.100.0; extra == "server"
Requires-Dist: uvicorn>=0.22.0; extra == "server"
Requires-Dist: websockets>=10.0; extra == "server"
Provides-Extra: remote
Requires-Dist: requests>=2.31.0; extra == "remote"
Requires-Dist: websocket-client>=1.8.0; extra == "remote"
Provides-Extra: schema
Requires-Dist: jsonschema>=4.0.0; extra == "schema"
Requires-Dist: rfc3987>=1.3.8; extra == "schema"
Provides-Extra: all
Requires-Dist: nekoconf[remote,schema,server]; extra == "all"
Provides-Extra: dev
Requires-Dist: pytest>=7.0.0; extra == "dev"
Requires-Dist: pytest-cov>=4.0.0; extra == "dev"
Requires-Dist: pytest-asyncio>=0.21.0; extra == "dev"
Requires-Dist: httpx>=0.27.0; extra == "dev"
Requires-Dist: nekoconf[all]; extra == "dev"
Provides-Extra: lint
Requires-Dist: flake8>=6.0.0; extra == "lint"
Requires-Dist: black>=23.0.0; extra == "lint"
Requires-Dist: isort>=5.0.0; extra == "lint"
Dynamic: license-file
